cathartidae/__init__.py
cathartidae/builder_args.py
cathartidae/constants.py
cathartidae/control_decorator.py
cathartidae/control_decorator_builder.py
cathartidae/control_decorators.py
cathartidae/abstract_block/__init__.py
cathartidae/abstract_block/abstract_block.py
cathartidae/abstract_block/for_block.py
cathartidae/abstract_block/if_block.py
cathartidae/abstract_block/while_block.py
cathartidae/abstract_block/with_block.py
cathartidae/lib/__init__.py
cathartidae/lib/build_decorators.py
cathartidae/lib/decorator_conversion.py
cathartidae/lib/echos.py
cathartidae/unit_tests/__init__.py
cathartidae/unit_tests/basic_decorated_test_methods.py
cathartidae/unit_tests/test_decorators_against_different_functions.py
cathartidae/unit_tests/test_decorators_basic.py
cathartidae/unit_tests/mocking_utils/__init__.py
cathartidae-1.0.1.dist-info/LICENSE
cathartidae-1.0.1.dist-info/METADATA
cathartidae-1.0.1.dist-info/WHEEL
cathartidae-1.0.1.dist-info/top_level.txt
cathartidae-1.0.1.dist-info/RECORD
